xattrs-0.0.2.dist-info/METADATA
xattrs-0.0.2.dist-info/WHEEL
xattrs-0.0.2.dist-info/entry_points.txt
xattrs-0.0.2.dist-info/licenses/LICENSE
xattrs/__init__.py
xattrs/_compat/__init__.py
xattrs/_compat/typing.py
xattrs/_compat/typing_internal.py
xattrs/_funcs.py
xattrs/_guards.py
xattrs/_helpers.py
xattrs/_metadata.py
xattrs/_serde.py
xattrs/_struct_funcs.py
xattrs/_tree.py
xattrs/_types.py
xattrs/_typing.py
xattrs/_uni.py
xattrs/abc.py
xattrs/attrs.py
xattrs/attrs.pyi
xattrs/base.py
xattrs/constants.py
xattrs/converters.py
xattrs/dataclasses.py
xattrs/deserializer.py
xattrs/dispatcher.py
xattrs/exceptions.py
xattrs/filters.py
xattrs/preconf/csv.py
xattrs/preconf/json.py
xattrs/preconf/msgpack.py
xattrs/preconf/toml.py
xattrs/preconf/yaml.py
xattrs/py.typed
xattrs/serializer.py
xattrs/strategies/__init__.py
xattrs/strategy.py
xattrs/typing.py
xattrs-0.0.2.dist-info/RECORD
