Metadata-Version: 2.1
Name: xattrs
Version: 0.0.2
Summary: An eXtensible serializing and deserializing toolkit for Python strucuted classes
Keywords: attrs,cattrs,serde,json,schema
Author-Email: Lanqing Huang <lqhuang@outlook.com>
License: MIT
Classifier: Development Status :: 3 - Alpha
Classifier: Programming Language :: Python
Classifier: Programming Language :: Python :: 3
Classifier: Programming Language :: Python :: 3 :: Only
Classifier: Programming Language :: Python :: 3.9
Classifier: Programming Language :: Python :: 3.10
Classifier: Programming Language :: Python :: 3.11
Classifier: Programming Language :: Python :: 3.12
Classifier: Programming Language :: Python :: 3.13
Classifier: Programming Language :: Python :: 3.14
Classifier: Programming Language :: Python :: Implementation :: CPython
Classifier: License :: OSI Approved :: MIT License
Classifier: Operating System :: POSIX
Classifier: Typing :: Typed
Project-URL: Documentation, https://github.com/lqhuang/xattrs#readme
Project-URL: Issues, https://github.com/lqhuang/xattrs/issues
Project-URL: Source, https://github.com/lqhuang/xattrs
Requires-Python: >=3.9
Requires-Dist: attrs
Requires-Dist: typing_extensions
Requires-Dist: datetype
Provides-Extra: yaml
Requires-Dist: ruamel-yaml>=0.18.1; extra == "yaml"
Provides-Extra: toml
Requires-Dist: tomlkit; extra == "toml"
Provides-Extra: ujson
Requires-Dist: ujson; extra == "ujson"
Provides-Extra: msgpack
Requires-Dist: msgspec; extra == "msgpack"
Provides-Extra: all
Requires-Dist: xattrs[toml]; extra == "all"
Requires-Dist: xattrs[yaml]; extra == "all"
Requires-Dist: xattrs[ujson]; extra == "all"
Requires-Dist: xattrs[msgpack]; extra == "all"
